{
  "_meta": {
    "team": "OKC",
    "player": "Jalen Williams",
    "source": "NBA/ESPN Trade History Research",
    "sourceUrl": "https://www.basketball-reference.com/players/w/willija06.html",
    "originYear": 2022,
    "depth": 1,
    "lastUpdated": "2026-02-10"
  },
  "tree": {
    "type": "player",
    "name": "Jalen Williams",
    "acquisitionType": "draft",
    "date": "2022-06-23",
    "draftPick": 12,
    "draftRound": 1,
    "currentTeam": "OKC",
    "tradeDescription": "Drafted 12th overall by Thunder",
    "note": "Santa Clara product, All-Star caliber, versatile two-way wing, homegrown talent",
    "isOrigin": true
  }
}
