{
  "_meta": {
    "team": "BKN",
    "player": "Josh Minott",
    "source": "Basketball-Reference",
    "sourceUrl": "https://www.basketball-reference.com/players/m/minotjo01.html",
    "originYear": 2022,
    "depth": 1,
    "lastUpdated": "2026-03-01"
  },
  "tree": {
    "type": "player",
    "name": "Josh Minott",
    "acquisitionType": "trade",
    "date": "2026-02-05",
    "currentTeam": "BKN",
    "tradePartner": "BOS",
    "tradeDescription": "BKN traded cash to Boston Celtics for Josh Minott. Boston received a trade exception.",
    "note": "Athletic forward, originally drafted #45 by MIN in 2022. BKN acquired him for cash at the 2026 deadline.",
    "assetsGivenUp": [
      {
        "type": "other",
        "name": "Cash considerations",
        "acquisitionType": "original",
        "date": "2026-02-05",
        "note": "Cash sent to Boston Celtics.",
        "isOrigin": true
      }
    ]
  }
}
