{
  "_meta": {
    "team": "MIN",
    "player": "Johnny Juzang",
    "source": "Basketball-Reference",
    "sourceUrl": "https://www.basketball-reference.com/players/j/juzanjo01.html",
    "lastUpdated": "2026-03-01"
  },
  "tree": {
    "type": "player",
    "name": "Johnny Juzang",
    "acquisitionType": "free-agent",
    "date": "2025-08-01",
    "currentTeam": "MIN",
    "note": "UCLA guard, undrafted in 2022. Spent 3 years with Utah Jazz. Signed 1-year non-guaranteed deal with MIN.",
    "isOrigin": true
  }
}